D4Xgui/Welcome.py
D4Xgui/__init__.py
D4Xgui/run.py
D4Xgui/.streamlit/config.toml
D4Xgui/.streamlit/secrets.toml
D4Xgui/pages/01_Data_IO.py
D4Xgui/pages/03_Baseline_correction.py
D4Xgui/pages/04_Processing.py
D4Xgui/pages/05_Standardization_Results.py
D4Xgui/pages/06_Dual_Clumped_Space.py
D4Xgui/pages/07_Discover_Results.py
D4Xgui/pages/08_D47crunch_plots.py
D4Xgui/pages/100_Save_and_Reload.py
D4Xgui/pages/97_Database_Management.py
D4Xgui/pages/99_st.session_state.py_not
D4Xgui/pages/__init__.py
D4Xgui/static/D4Xgui_logo_master_red08.png
D4Xgui/static/SampleDatabase.xlsx
D4Xgui/static/exampleIntensities_anonymized.xlsx
D4Xgui/static/exampleReplicates_anonymized.xlsx
D4Xgui/tools/Pysotope_fork.py
D4Xgui/tools/__init__.py
D4Xgui/tools/authenticator.py
D4Xgui/tools/calc_temperature.py
D4Xgui/tools/commons.py
D4Xgui/tools/database.py
D4Xgui/tools/init_params.py
D4Xgui/tools/page_config.py
D4Xgui/tools/sidebar_logo.py
d4xgui-1.0.2.dist-info/licenses/LICENSE
d4xgui-1.0.2.dist-info/METADATA
d4xgui-1.0.2.dist-info/WHEEL
d4xgui-1.0.2.dist-info/entry_points.txt
d4xgui-1.0.2.dist-info/top_level.txt
d4xgui-1.0.2.dist-info/RECORD
