Metadata-Version: 2.4
Name: D4Xgui
Version: 1.0.2
Summary: Processing app for mass-spectrometric CO₂ clumped isotope (∆₄₇, ∆₄₈, ∆₄₉) data
Author-email: Miguel Bernecker <mbernecker@posteo.de>
License: MIT
Project-URL: Homepage, https://github.com/itsMig/D4Xgui
Project-URL: Repository, https://github.com/itsMig/D4Xgui.git
Project-URL: Bug Tracker, https://github.com/itsMig/D4Xgui/issues
Project-URL: Documentation, https://github.com/itsMig/D4Xgui/blob/main/README.md
Keywords: mass-spectrometry,isotope,clumped-isotope,paleoclimate,geochemistry
Classifier: Development Status :: 4 - Beta
Classifier: Environment :: Web Environment
Classifier: Intended Audience :: Science/Research
Classifier: License :: OSI Approved :: MIT License
Classifier: Natural Language :: English
Classifier: Operating System :: OS Independent
Classifier: Programming Language :: Python :: 3.12
Classifier: Topic :: Scientific/Engineering :: Chemistry
Classifier: Topic :: Scientific/Engineering :: Physics
Requires-Python: >=3.12
License-File: LICENSE
Requires-Dist: streamlit>=1.28.0
Requires-Dist: altair
Requires-Dist: blinker
Requires-Dist: cachetools
Requires-Dist: click
Requires-Dist: gitdb
Requires-Dist: GitPython
Requires-Dist: jinja2
Requires-Dist: jsonschema
Requires-Dist: markdown
Requires-Dist: pillow
Requires-Dist: protobuf
Requires-Dist: pyarrow
Requires-Dist: pydeck
Requires-Dist: pympler
Requires-Dist: requests
Requires-Dist: rich
Requires-Dist: tenacity
Requires-Dist: toml
Requires-Dist: tornado
Requires-Dist: tzdata
Requires-Dist: tzlocal
Requires-Dist: validators
Requires-Dist: watchdog
Requires-Dist: python-dateutil
Requires-Dist: pytz
Requires-Dist: numpy>=1.24.0
Requires-Dist: pandas>=2.0.0
Requires-Dist: openpyxl
Requires-Dist: xlrd
Requires-Dist: xlsxwriter
Requires-Dist: plotly
Requires-Dist: scipy
Requires-Dist: D47crunch>=2.4.3
Requires-Dist: D47calib
Requires-Dist: ogls
Requires-Dist: lmfit
Requires-Dist: uncertainties
Requires-Dist: streamlit-extras
Requires-Dist: sphinx
Requires-Dist: sphinx-autobuild
Dynamic: license-file
